pymilvus/model/__init__.py
pymilvus/model/base.py
pymilvus/model/dense/__init__.py
pymilvus/model/dense/cohere.py
pymilvus/model/dense/instructor.py
pymilvus/model/dense/jinaai.py
pymilvus/model/dense/mistralai.py
pymilvus/model/dense/model2vec_embed.py
pymilvus/model/dense/nomic.py
pymilvus/model/dense/onnx.py
pymilvus/model/dense/openai.py
pymilvus/model/dense/sentence_transformer.py
pymilvus/model/dense/tei.py
pymilvus/model/dense/voyageai.py
pymilvus/model/dense/instructor_embedding/instructor_impl.py
pymilvus/model/hybrid/__init__.py
pymilvus/model/hybrid/bge_m3.py
pymilvus/model/hybrid/mgte.py
pymilvus/model/hybrid/mgte_embedding/gte_impl.py
pymilvus/model/reranker/__init__.py
pymilvus/model/reranker/bgereranker.py
pymilvus/model/reranker/cohere.py
pymilvus/model/reranker/cross_encoder.py
pymilvus/model/reranker/jinaai.py
pymilvus/model/reranker/tei.py
pymilvus/model/reranker/voyageai.py
pymilvus/model/sparse/__init__.py
pymilvus/model/sparse/splade.py
pymilvus/model/sparse/utils.py
pymilvus/model/sparse/bm25/__init__.py
pymilvus/model/sparse/bm25/bm25.py
pymilvus/model/sparse/bm25/lang.yaml
pymilvus/model/sparse/bm25/tokenizers.py
pymilvus/model/sparse/splade_embedding/splade_impl.py
pymilvus/model/utils/__init__.py
pymilvus/model/utils/dependency_control.py
pymilvus_model-0.3.1.dist-info/LICENSE
pymilvus_model-0.3.1.dist-info/METADATA
pymilvus_model-0.3.1.dist-info/WHEEL
pymilvus_model-0.3.1.dist-info/top_level.txt
pymilvus_model-0.3.1.dist-info/RECORD
